package_template_handler.py
sceptre_package_template_handler-0.1.1.dist-info/METADATA
sceptre_package_template_handler-0.1.1.dist-info/WHEEL
sceptre_package_template_handler-0.1.1.dist-info/entry_points.txt
sceptre_package_template_handler-0.1.1.dist-info/top_level.txt
sceptre_package_template_handler-0.1.1.dist-info/RECORD
